{
  "_fv": 10,
  "_type": "recipe",
  "definition": {
    "recipeType": "Crafting",
    "xpReward": 0.0,
    "cookingTime": 200,
    "recipeRetstackSize": 1,
    "group": "",
    "recipeShapeless": true,
    "recipeSlots": [
      {
        "value": ""
      },
      {
        "value": ""
      },
      {
        "value": ""
      },
      {
        "value": "CUSTOM:CornDog"
      },
      {
        "value": "Blocks.OBSIDIAN"
      },
      {
        "value": "Items.GOLD_NUGGET"
      },
      {
        "value": ""
      },
      {
        "value": ""
      },
      {
        "value": ""
      }
    ],
    "recipeReturnStack": {
      "value": "CUSTOM:NetherCornDog"
    },
    "name": "nether_corn_dog_recipe",
    "namespace": "mod"
  }
}